zos_mcp_client/__init__.py
zos_mcp_client/main.py
zos_mcp_client-1.0.0.dist-info/licenses/LICENSE
zos_mcp_client-1.0.0.dist-info/METADATA
zos_mcp_client-1.0.0.dist-info/WHEEL
zos_mcp_client-1.0.0.dist-info/entry_points.txt
zos_mcp_client-1.0.0.dist-info/top_level.txt
zos_mcp_client-1.0.0.dist-info/RECORD
