Metadata-Version: 2.4
Name: zos-mcp-client
Version: 1.0.0
Summary: MCP client for z/OS mainframe operations with Amazon Q CLI
Author: Souma S Ghosh
License: MIT
Project-URL: Homepage, https://github.com/yourusername/zos-mcp-client
Project-URL: Repository, https://github.com/yourusername/zos-mcp-client
Project-URL: Issues, https://github.com/yourusername/zos-mcp-client/issues
Keywords: mcp,mainframe,zos,amazon-q,cli
Classifier: Development Status :: 4 - Beta
Classifier: Intended Audience :: Developers
Classifier: License :: OSI Approved :: MIT License
Classifier: Programming Language :: Python :: 3.9
Classifier: Programming Language :: Python :: 3.10
Classifier: Programming Language :: Python :: 3.11
Classifier: Programming Language :: Python :: 3.12
Requires-Python: >=3.8
License-File: LICENSE
Requires-Dist: websockets>=11.0
Dynamic: license-file
